{
  "doc_id": "1hWY2p6oVksEZ77L0-dCL5PsKp2r64nK-2MVtOEbs5IM",
  "link": "https://docs.google.com/document/d/1hWY2p6oVksEZ77L0-dCL5PsKp2r64nK-2MVtOEbs5IM",
  "timestamp": "12/15/2025 15:35:13",
  "display_name": "Nozomio",
  "legal_name": "Nozomio Inc.",
  "company_name": "Nozomio",
  "system_description": "A product lab building fully autonomous engineers and tools for the age of AI.",
  "audit_end_date": "December 4, 2025",
  "observation_period": "",
  "infra_provider": "GCP",
  "website": "https://nozomio.com",
  "contact_email": "founders@nozomio.com",
  "address": "",
  "report_type": "SOC 2 Type 1",
  "pdf_file": "1hWY2p6oVksEZ77L0-dCL5PsKp2r64nK-2MVtOEbs5IM.pdf",
  "txt_file": "1hWY2p6oVksEZ77L0-dCL5PsKp2r64nK-2MVtOEbs5IM.txt",
  "has_report": true
}